twiddlepy/__init__.py
twiddlepy/command_line.py
twiddlepy/config.py
twiddlepy/driver.py
twiddlepy/ds_manager.py
twiddlepy/exceptions.py
twiddlepy/mapper.py
twiddlepy/repo_file.py
twiddlepy/repo_manager.py
twiddlepy/repo_solr.py
twiddlepy/utils.py
twiddlepy/connectors/__init__.py
twiddlepy/connectors/pysolr.py
twiddlepy/data/solr_fieldtype_defaults.csv
twiddlepy/data/twiddle_defaults.cfg
twiddlepy/data/twiddlepy_defaults.cfg
twiddlepy/datasources/__init__.py
twiddlepy/datasources/ds_base.py
twiddlepy/datasources/ds_file.py
twiddlepy/datasources/ds_metadata.py
twiddlepy/datasources/ds_mongo.py
twiddlepy/datasources/ds_sql.py
twiddlepy-0.1.3.dist-info/LICENSE
twiddlepy-0.1.3.dist-info/METADATA
twiddlepy-0.1.3.dist-info/WHEEL
twiddlepy-0.1.3.dist-info/entry_points.txt
twiddlepy-0.1.3.dist-info/top_level.txt
twiddlepy-0.1.3.dist-info/RECORD
