Metadata-Version: 2.1
Name: twiddlepy
Version: 0.1.3
Summary: Extract, Transform and Load pipeline application
Home-page: https://github.com/mediaintegration/twiddlepy
Author: Media Integration Technologies Ltd.
Author-email: info@mediaintegration.co.uk
License: UNKNOWN
Platform: UNKNOWN
Requires-Dist: certifi (==2018.11.29)
Requires-Dist: chardet (==3.0.4)
Requires-Dist: cx-oracle (==7.1.1)
Requires-Dist: cython (==0.29.6)
Requires-Dist: idna (==2.8)
Requires-Dist: kazoo (==2.6.1)
Requires-Dist: numpy (==1.16.2)
Requires-Dist: pandas-schema (==0.3.2)
Requires-Dist: pandas (==0.24.1)
Requires-Dist: pymongo (==3.7.2)
Requires-Dist: pymssql (==2.1.4)
Requires-Dist: pymysql (==0.9.3)
Requires-Dist: python-dateutil (==2.8.0)
Requires-Dist: pytz (==2018.9)
Requires-Dist: requests (==2.21.0)
Requires-Dist: simplejson (==3.16.0)
Requires-Dist: six (==1.12.0)
Requires-Dist: sqlalchemy (==1.3.0)
Requires-Dist: urllib3 (==1.24.1)
Requires-Dist: xlrd (==1.2.0)
